AsposeEmailCloudSdk/__init__.py
AsposeEmailCloudSdk/api_client.py
AsposeEmailCloudSdk/configuration.py
AsposeEmailCloudSdk/rest.py
AsposeEmailCloudSdk/api/__init__.py
AsposeEmailCloudSdk/api/ai_bcr_api.py
AsposeEmailCloudSdk/api/ai_group.py
AsposeEmailCloudSdk/api/ai_name_api.py
AsposeEmailCloudSdk/api/api_base.py
AsposeEmailCloudSdk/api/calendar_api.py
AsposeEmailCloudSdk/api/client_account_api.py
AsposeEmailCloudSdk/api/client_folder_api.py
AsposeEmailCloudSdk/api/client_group.py
AsposeEmailCloudSdk/api/client_message_api.py
AsposeEmailCloudSdk/api/client_thread_api.py
AsposeEmailCloudSdk/api/cloud_storage_group.py
AsposeEmailCloudSdk/api/contact_api.py
AsposeEmailCloudSdk/api/disposable_email_api.py
AsposeEmailCloudSdk/api/email_api.py
AsposeEmailCloudSdk/api/email_cloud.py
AsposeEmailCloudSdk/api/email_config_api.py
AsposeEmailCloudSdk/api/file_api.py
AsposeEmailCloudSdk/api/folder_api.py
AsposeEmailCloudSdk/api/mapi_calendar_api.py
AsposeEmailCloudSdk/api/mapi_contact_api.py
AsposeEmailCloudSdk/api/mapi_group.py
AsposeEmailCloudSdk/api/mapi_message_api.py
AsposeEmailCloudSdk/api/storage_api.py
AsposeEmailCloudSdk/models/__init__.py
AsposeEmailCloudSdk/models/ai_bcr_image.py
AsposeEmailCloudSdk/models/ai_bcr_image_storage_file.py
AsposeEmailCloudSdk/models/ai_bcr_options.py
AsposeEmailCloudSdk/models/ai_bcr_parse_request.py
AsposeEmailCloudSdk/models/ai_bcr_parse_storage_request.py
AsposeEmailCloudSdk/models/ai_name_complete_request.py
AsposeEmailCloudSdk/models/ai_name_component.py
AsposeEmailCloudSdk/models/ai_name_component_list.py
AsposeEmailCloudSdk/models/ai_name_cultural_context.py
AsposeEmailCloudSdk/models/ai_name_expand_request.py
AsposeEmailCloudSdk/models/ai_name_extracted.py
AsposeEmailCloudSdk/models/ai_name_extracted_component.py
AsposeEmailCloudSdk/models/ai_name_extracted_list.py
AsposeEmailCloudSdk/models/ai_name_format_request.py
AsposeEmailCloudSdk/models/ai_name_formatted.py
AsposeEmailCloudSdk/models/ai_name_gender_hypothesis.py
aspose_email_cloud-21.9.0.dist-info/METADATA
aspose_email_cloud-21.9.0.dist-info/WHEEL
aspose_email_cloud-21.9.0.dist-info/top_level.txt
aspose_email_cloud-21.9.0.dist-info/RECORD
