Metadata-Version: 2.1
Name: aspose-email-cloud
Version: 21.9.0
Summary: Aspose.Email Cloud API
Home-page: https://products.aspose.cloud/email/family
Author-email: 
License: License :: OSI Approved :: MIT License
Keywords: Swagger,Aspose.Email Cloud API
Platform: UNKNOWN
Classifier: License :: OSI Approved :: MIT License
Requires-Dist: certifi (>=2017.4.17)
Requires-Dist: python-dateutil (>=2.1)
Requires-Dist: six (>=1.10)
Requires-Dist: urllib3 (>=1.23)
